{
    "options":{
        "title": {
            "text": "汽车价格对比折线图"
        },
        "tooltip": {
            "trigger": "axis"
        },
        "legend" : {
            "data" : ["甲车型", "乙车型"]
            ,
            "textStyle" :{
                              
                "color": "#ffffff"
                            }
        },
        "grid": {
            "left": "3%",
            " right": "4%",
            " bottom": "3%",
            "top":"15%",
            "containLabel": true
        },
        "toolbox": {
            "feature": {
                "saveAsImage": {}
            }
        },
        "xAxis": {
            "type": "category",
            "boundaryGap": false,
            "data": ["一月", "二月", "三月", "四月", "五月", "六月"]
        },
        "yAxis": {
            "type": "value"
        },
        "series": [
            {
                "name": "甲车型",
                "type": "line",
                "stack": "售价",
                "data": [120, 132, 101, 134, 90, 230, 210]
            },
            {
                "name": "乙车型",
                "type": "line",
                "stack": "售价",
                "data" : [220, 182, 191, 234, 290, 330, 310]
            }
        ]
    }
}